easylogcli/__init__.py
easylogcli/easylog.py
easylogcli/util.py
easylogcli-1.2.9.dist-info/METADATA
easylogcli-1.2.9.dist-info/WHEEL
easylogcli-1.2.9.dist-info/top_level.txt
easylogcli-1.2.9.dist-info/RECORD
