Metadata-Version: 2.1
Name: easylogcli
Version: 1.2.9
Summary: [easylog](https://github.com/prprprus/easylog) 的 Python 客户端实现
Home-page: https://github.com/prprprus/easylog-client
License: UNKNOWN
Platform: UNKNOWN
Classifier: Programming Language :: Python :: 3
Classifier: License :: OSI Approved :: BSD License
Classifier: Operating System :: OS Independent
